{
    "utenti": [
        {
            "email": "prova1@",
            "password": "prova1",
            "username": "prova1",
            "address": [
                "127.0.0.1",
                57845
            ]
        },
        {
            "email": "prova2@",
            "password": "prova2",
            "username": "prova2",
            "address": [
                "127.0.0.1",
                57846
            ]
        },
        {
            "email": "b@",
            "password": "b",
            "username": "b",
            "address": [
                "127.0.0.1",
                61918
            ]
        },
        {
            "email": "a@",
            "password": "a",
            "username": "a",
            "address": [
                "127.0.0.1",
                49822
            ]
        }
    ]
}